{"mode": "collect", "collector_tag": "run_sheetbook_collect_pilot_samples", "user_id": 61, "username": "sheetbook_pilot_collector", "days": 14, "clear_result": {"deleted_events": 0, "deleted_sheetbook_objects": 0}, "requested": {"home_count": 5, "create_count": 5, "action_count": 3, "action_count_mode": "auto", "archive_event_count": 5, "archive_batch_size": 3, "next_due_date": "2026-03-05"}, "flow_result": {"selected_sheetbook_ids": [104, 103, 102], "status": {"home_status_codes": [], "home_fallback_events": 5, "home_errors": [], "quick_create_status_codes": [302, 302, 302, 302, 302], "action_fallback_events": 3, "bulk_archive_status_codes": [{"action": "archive", "status_code": 302}, {"action": "unarchive", "status_code": 302}, {"action": "archive", "status_code": 302}, {"action": "unarchive", "status_code": 302}, {"action": "archive", "status_code": 302}]}}, "user_before": {"workspace_home_opened": 0, "home_source_sheetbook_created": 0, "home_source_action_execute_requested": 0, "archive_event_count": 0}, "user_after": {"workspace_home_opened": 5, "home_source_sheetbook_created": 5, "home_source_action_execute_requested": 3, "archive_event_count": 5}, "user_delta": {"archive_event_count": 5, "home_source_action_execute_requested": 3, "home_source_sheetbook_created": 5, "workspace_home_opened": 5}, "global_before": {"workspace_home_opened": 0, "home_source_sheetbook_created": 0, "home_source_action_execute_requested": 0, "archive_event_count": 0}, "global_after": {"workspace_home_opened": 5, "home_source_sheetbook_created": 5, "home_source_action_execute_requested": 3, "archive_event_count": 5}, "global_delta": {"archive_event_count": 5, "home_source_action_execute_requested": 3, "home_source_sheetbook_created": 5, "workspace_home_opened": 5}, "next_steps": ["python scripts/run_sheetbook_release_readiness.py --days 14", "python scripts/run_sheetbook_sample_gap_summary.py --days 14", "python scripts/run_sheetbook_daily_start_bundle.py --days 14 --due-date 2026-03-05 --allow-pilot-hold-for-beta"], "output": "C:\\Users\\kakio\\eduitit\\docs\\handoff\\smoke_sheetbook_collect_samples_bundle_latest.json"}
